pytest_tcp/__init__.py
pytest_tcp/plugin.py
pytest_tcp-0.1.1.dist-info/LICENSE
pytest_tcp-0.1.1.dist-info/METADATA
pytest_tcp-0.1.1.dist-info/WHEEL
pytest_tcp-0.1.1.dist-info/entry_points.txt
pytest_tcp-0.1.1.dist-info/top_level.txt
pytest_tcp-0.1.1.dist-info/RECORD
