Metadata-Version: 2.1
Name: pytest-tcp
Version: 0.1.1
Summary: A Pytest plugin for test prioritization
Home-page: https://github.com/softwareTestingResearch/pytest-tcp
Author: softwareTestingResearch
Author-email: testingresearch4all@gmail.com
Maintainer: softwareTestingResearch
Maintainer-email: testingresearch4all@gmail.com
License: MIT
Keywords: pytest,py.test,test prioritization,test order,test ordering,test ranking
Classifier: Development Status :: 4 - Beta
Classifier: Framework :: Pytest
Classifier: Intended Audience :: Developers
Classifier: Topic :: Software Development :: Testing
Classifier: Programming Language :: Python
Classifier: Programming Language :: Python :: 3
Classifier: Programming Language :: Python :: 3.5
Classifier: Programming Language :: Python :: 3.6
Classifier: Programming Language :: Python :: 3.7
Classifier: Programming Language :: Python :: 3.8
Classifier: Programming Language :: Python :: 3 :: Only
Classifier: Programming Language :: Python :: Implementation :: CPython
Classifier: Programming Language :: Python :: Implementation :: PyPy
Classifier: Operating System :: OS Independent
Classifier: License :: OSI Approved :: MIT License
Requires-Python: >=3.5
License-File: LICENSE
Requires-Dist: pytest >=7.4.3
Requires-Dist: numpy
